pyhanko_certvalidator/__init__.py
pyhanko_certvalidator/_asyncio_compat.py
pyhanko_certvalidator/_state.py
pyhanko_certvalidator/_types.py
pyhanko_certvalidator/asn1_types.py
pyhanko_certvalidator/authority.py
pyhanko_certvalidator/context.py
pyhanko_certvalidator/errors.py
pyhanko_certvalidator/name_trees.py
pyhanko_certvalidator/path.py
pyhanko_certvalidator/policy_decl.py
pyhanko_certvalidator/policy_tree.py
pyhanko_certvalidator/py.typed
pyhanko_certvalidator/registry.py
pyhanko_certvalidator/util.py
pyhanko_certvalidator/validate.py
pyhanko_certvalidator/version.py
pyhanko_certvalidator/fetchers/__init__.py
pyhanko_certvalidator/fetchers/api.py
pyhanko_certvalidator/fetchers/common_utils.py
pyhanko_certvalidator/fetchers/aiohttp_fetchers/__init__.py
pyhanko_certvalidator/fetchers/aiohttp_fetchers/cert_fetch_client.py
pyhanko_certvalidator/fetchers/aiohttp_fetchers/crl_client.py
pyhanko_certvalidator/fetchers/aiohttp_fetchers/ocsp_client.py
pyhanko_certvalidator/fetchers/aiohttp_fetchers/util.py
pyhanko_certvalidator/fetchers/requests_fetchers/__init__.py
pyhanko_certvalidator/fetchers/requests_fetchers/cert_fetch_client.py
pyhanko_certvalidator/fetchers/requests_fetchers/crl_client.py
pyhanko_certvalidator/fetchers/requests_fetchers/ocsp_client.py
pyhanko_certvalidator/fetchers/requests_fetchers/util.py
pyhanko_certvalidator/ltv/__init__.py
pyhanko_certvalidator/ltv/ades_past.py
pyhanko_certvalidator/ltv/errors.py
pyhanko_certvalidator/ltv/poe.py
pyhanko_certvalidator/ltv/time_slide.py
pyhanko_certvalidator/ltv/types.py
pyhanko_certvalidator/revinfo/__init__.py
pyhanko_certvalidator/revinfo/_err_gather.py
pyhanko_certvalidator/revinfo/archival.py
pyhanko_certvalidator/revinfo/constants.py
pyhanko_certvalidator/revinfo/manager.py
pyhanko_certvalidator/revinfo/validate_crl.py
pyhanko_certvalidator/revinfo/validate_ocsp.py
pyhanko_certvalidator-0.26.6.dist-info/LICENSE
pyhanko_certvalidator-0.26.6.dist-info/METADATA
pyhanko_certvalidator-0.26.6.dist-info/WHEEL
pyhanko_certvalidator-0.26.6.dist-info/top_level.txt
pyhanko_certvalidator-0.26.6.dist-info/RECORD
