Metadata-Version: 2.2
Name: pyhanko-certvalidator
Version: 0.26.6
Summary: Validates X.509 certificates and paths; forked from wbond/certvalidator
Author-email: Matthias Valvekens <dev@mvalvekens.be>
License: MIT
Project-URL: Homepage, https://github.com/MatthiasValvekens/certvalidator
Keywords: crypto,pki,x509,certificate,crl,ocsp
Classifier: Development Status :: 4 - Beta
Classifier: Intended Audience :: Developers
Classifier: License :: OSI Approved :: MIT License
Classifier: Programming Language :: Python :: 3
Classifier: Programming Language :: Python :: 3.8
Classifier: Programming Language :: Python :: 3.9
Classifier: Programming Language :: Python :: 3.10
Classifier: Programming Language :: Python :: 3.11
Classifier: Programming Language :: Python :: 3.12
Classifier: Programming Language :: Python :: 3.13
Classifier: Topic :: Security :: Cryptography
Requires-Python: >=3.8
License-File: LICENSE
Requires-Dist: asn1crypto>=1.5.1
Requires-Dist: oscrypto>=1.1.0
Requires-Dist: cryptography>=41.0.5
Requires-Dist: uritools>=3.0.1
Requires-Dist: requests>=2.31.0
Provides-Extra: async-http
Requires-Dist: aiohttp<3.12,>=3.8; extra == "async-http"
Provides-Extra: testing
Requires-Dist: pytest>=6.1.1; extra == "testing"
Requires-Dist: pytest-cov<6.1,>=4.0; extra == "testing"
Requires-Dist: freezegun>=1.1.0; extra == "testing"
Requires-Dist: aiohttp<3.12,>=3.8; extra == "testing"
Requires-Dist: pytest-aiohttp<1.2.0,>=1.0.4; extra == "testing"
Requires-Dist: pyhanko-certvalidator[async-http]; extra == "testing"
Provides-Extra: mypy
Requires-Dist: types-requests; extra == "mypy"
Requires-Dist: pyhanko-certvalidator[testing]; extra == "mypy"
